setup.py
odoo/addons/correos_somconnexio/CHANGELOG.md
odoo/addons/correos_somconnexio/README.rst
odoo/addons/correos_somconnexio/__init__.py
odoo/addons/correos_somconnexio/__manifest__.py
odoo/addons/correos_somconnexio/correos_services/__init__.py
odoo/addons/correos_somconnexio/correos_services/shipment.py
odoo/addons/correos_somconnexio/data/queue_job_config.xml
odoo/addons/correos_somconnexio/helpers/__init__.py
odoo/addons/correos_somconnexio/helpers/job_retry_utils.py
odoo/addons/correos_somconnexio/helpers/language.py
odoo/addons/correos_somconnexio/i18n/ca_ES.po
odoo/addons/correos_somconnexio/i18n/es.po
odoo/addons/correos_somconnexio/models/__init__.py
odoo/addons/correos_somconnexio/models/crm_lead.py
odoo/addons/correos_somconnexio/tests/__init__.py
odoo/addons/correos_somconnexio/tests/correos_services/__init__.py
odoo/addons/correos_somconnexio/tests/correos_services/test_shipment.py
odoo/addons/correos_somconnexio/tests/listeners/__init__.py
odoo/addons/correos_somconnexio/tests/listeners/test_crm_lead_listener.py
odoo/addons/correos_somconnexio/tests/models/__init__.py
odoo/addons/correos_somconnexio/tests/models/test_crm_lead.py
odoo_addon_correos_somconnexio.egg-info/PKG-INFO
odoo_addon_correos_somconnexio.egg-info/SOURCES.txt
odoo_addon_correos_somconnexio.egg-info/dependency_links.txt
odoo_addon_correos_somconnexio.egg-info/not-zip-safe
odoo_addon_correos_somconnexio.egg-info/requires.txt
odoo_addon_correos_somconnexio.egg-info/top_level.txt